[
{"biz_name": "Mutual of America Financial Group"},
{"biz_name": "Bernard Robinson & Co. LLP"},
{"biz_name": "Greg W. Isley CPA, PA"},
{"biz_name": "KeeForce"},
{"biz_name": "Pavillon Treatment Center"},
{"biz_name": "Recovery Communities of North Carolina"},
{"biz_name": "Johnson Lambert LLP"},
{"biz_name": "Fulbright & Fulbright, CPA, PA"},
{"biz_name": "Cherry Bekaert LLP"},
{"biz_name": "CLA"},
{"biz_name": "Center for Chiropractic and Wellness"},
{"biz_name": "Triangle Acupuncture Clinic"},
{"biz_name": "Pavillon Treatment Center"},
{"biz_name": "LBE Business solutions LLC"},
{"biz_name": "Dani Moe Administration Services"},
{"biz_name": "CompleatKidz"},
{"biz_name": "Developmental Therapy Assoc INC"}
]